<?xml version="1.0" ?>
<FREQUENCY>
	<LETTERS>
		<LETTER name="A" value="8.2"/>
		<LETTER name="B" value="1.5"/>
		<LETTER name="C" value="2.8"/>
		<LETTER name="D" value="4.3"/>
		<LETTER name="E" value="12.7"/>
		<LETTER name="F" value="2.2"/>
		<LETTER name="G" value="2.0"/>
		<LETTER name="H" value="6.1"/>
		<LETTER name="I" value="7.0"/>
		<LETTER name="J" value="0.2"/>
		<LETTER name="K" value="0.8"/>
		<LETTER name="L" value="4.0"/>
		<LETTER name="M" value="2.4"/>
		<LETTER name="N" value="6.7"/>
		<LETTER name="O" value="7.5"/>
		<LETTER name="P" value="1.9"/>
		<LETTER name="Q" value="0.1"/>
		<LETTER name="R" value="6.0"/>
		<LETTER name="S" value="6.3"/>
		<LETTER name="T" value="9.1"/>
		<LETTER name="U" value="2.8"/>
		<LETTER name="V" value="1.0"/>
		<LETTER name="W" value="2.4"/>
		<LETTER name="X" value="0.2"/>
		<LETTER name="Y" value="2.0"/>
		<LETTER name="Z" value="0.1"/>
	</LETTERS>
</FREQUENCY>